EMGFlow/__init__.py
EMGFlow/access_files.py
EMGFlow/extract_features.py
EMGFlow/plot_signals.py
EMGFlow/preprocess_signals.py
EMGFlow/data/sample_data_01.csv
EMGFlow/data/sample_data_02.csv
EMGFlow/data/sample_data_03.csv
EMGFlow/data/sample_data_04.csv
emgflow-1.1.0.dist-info/METADATA
emgflow-1.1.0.dist-info/WHEEL
emgflow-1.1.0.dist-info/licenses/LICENSE
emgflow-1.1.0.dist-info/RECORD
