Metadata-Version: 2.4
Name: EMGFlow
Version: 1.1.0
Summary: A general EMG processing and feature extraction package.
Project-URL: Homepage, https://github.com/WiIIson/EMGFlow-Python-Package
Project-URL: Documentation, https://wiiison.github.io/EMGFlow-Python-Package/
Project-URL: Issues, https://github.com/WiIIson/EMGFlow-Python-Package/issues
Author-email: "D. William Conley" <william@cconley.ca>, "Steven R. Livingstone" <steven.livingstone@ontariotechu.ca>
Maintainer-email: "D. William Conley" <william@cconley.ca>
License-File: LICENSE
Classifier: License :: OSI Approved :: GNU General Public License v3 or later (GPLv3+)
Classifier: Operating System :: OS Independent
Classifier: Programming Language :: Python :: 3
Requires-Python: >=3.9
Requires-Dist: importlib-resources
Requires-Dist: matplotlib
Requires-Dist: nest-asyncio
Requires-Dist: numpy
Requires-Dist: pandas
Requires-Dist: scipy
Requires-Dist: shiny
Requires-Dist: tqdm
